lyre/__init__.py
lyre/evaluation.py
lyre/resolution.py
lyre/server.py
lyre-0.1.4.dist-info/entry_points.txt
lyre-0.1.4.dist-info/LICENSE
lyre-0.1.4.dist-info/METADATA
lyre-0.1.4.dist-info/WHEEL
lyre-0.1.4.dist-info/RECORD
