Metadata-Version: 2.1
Name: lyre
Version: 0.1.4
Summary: 
Author: Chris Chambers
Author-email: chris@peanutcode.com
Requires-Python: >=3.7,<4.0
Classifier: Programming Language :: Python :: 3
Classifier: Programming Language :: Python :: 3.7
Classifier: Programming Language :: Python :: 3.8
Classifier: Programming Language :: Python :: 3.9
Classifier: Programming Language :: Python :: 3.10
Classifier: Programming Language :: Python :: 3.11
Requires-Dist: aeval (>=0.1.3)
Requires-Dist: lsp (>=0.1.1,<0.2.0)
Requires-Dist: trio (>=0.22.2,<0.23.0)
